[
  {
    "ref": "tI6Z",
    "serverIndex": 0
  },
  {
    "ref": "s373",
    "baseRef": "tI6Z",
    "serverIndex": 1
  },
  {
    "ref": "95JQ",
    "baseRef": "tI6Z",
    "serverIndex": 2
  },
  {
    "ref": "WEOo",
    "baseRef": "tI6Z",
    "serverIndex": 3
  },
  {
    "ref": "nqtL",
    "baseRef": "s373",
    "serverIndex": 4
  },
  {
    "ref": "jFZo",
    "baseRef": "95JQ",
    "serverIndex": 5
  },
  {
    "ref": "BKxG",
    "baseRef": "WEOo",
    "serverIndex": 6
  },
  {
    "ref": "8S9P",
    "baseRef": "jFZo",
    "serverIndex": 7
  },
  {
    "ref": "jH4l",
    "baseRef": "nqtL",
    "serverIndex": 8
  },
  {
    "ref": "RFbg",
    "baseRef": "BKxG",
    "serverIndex": 9
  },
  {
    "ref": "PzUk",
    "baseRef": "8S9P",
    "serverIndex": 10
  },
  {
    "ref": "Rk4u",
    "baseRef": "jH4l",
    "serverIndex": 11
  },
  {
    "ref": "7SPW",
    "baseRef": "RFbg",
    "serverIndex": 12
  },
  {
    "ref": "35vG",
    "baseRef": "PzUk",
    "serverIndex": 13
  },
  {
    "ref": "GdwN",
    "baseRef": "Rk4u",
    "serverIndex": 14
  },
  {
    "ref": "2DSf",
    "baseRef": "7SPW",
    "serverIndex": 15
  },
  {
    "ref": "iDyW",
    "baseRef": "35vG",
    "serverIndex": 16
  },
  {
    "ref": "3Cfu",
    "baseRef": "GdwN",
    "serverIndex": 17
  },
  {
    "ref": "rR5V",
    "baseRef": "3Cfu",
    "serverIndex": 18
  },
  {
    "ref": "ixmn",
    "baseRef": "2DSf",
    "serverIndex": 19
  },
  {
    "ref": "jrSN",
    "baseRef": "iDyW",
    "serverIndex": 20
  },
  {
    "ref": "MX6C",
    "baseRef": "jrSN",
    "serverIndex": 21
  },
  {
    "ref": "cFNl",
    "baseRef": "rR5V",
    "serverIndex": 22
  },
  {
    "ref": "K3f1",
    "baseRef": "ixmn",
    "serverIndex": 23
  },
  {
    "ref": "bXKl",
    "baseRef": "cFNl",
    "serverIndex": 24
  },
  {
    "ref": "NGBa",
    "baseRef": "K3f1",
    "serverIndex": 25
  },
  {
    "ref": "y6FM",
    "baseRef": "NGBa",
    "serverIndex": 26
  },
  {
    "ref": "D8zi",
    "baseRef": "MX6C",
    "serverIndex": 27
  },
  {
    "ref": "A2lb",
    "baseRef": "bXKl",
    "serverIndex": 28
  },
  {
    "ref": "XijA",
    "baseRef": "y6FM",
    "serverIndex": 29
  },
  {
    "ref": "nQtL",
    "baseRef": "D8zi",
    "serverIndex": 30
  },
  {
    "ref": "Oc05",
    "baseRef": "A2lb",
    "serverIndex": 31
  },
  {
    "ref": "jo8e",
    "baseRef": "Oc05",
    "serverIndex": 32
  },
  {
    "ref": "G0W_",
    "baseRef": "XijA",
    "serverIndex": 33
  },
  {
    "ref": "V7Rc",
    "baseRef": "nQtL",
    "serverIndex": 34
  },
  {
    "ref": "1Wh6",
    "baseRef": "jo8e",
    "serverIndex": 35
  },
  {
    "ref": "Q4me",
    "baseRef": "G0W_",
    "serverIndex": 36
  },
  {
    "ref": "wnjI",
    "baseRef": "1Wh6",
    "serverIndex": 37
  },
  {
    "ref": "P6Q3",
    "baseRef": "Q4me",
    "serverIndex": 38
  },
  {
    "ref": "jSwy",
    "baseRef": "V7Rc",
    "serverIndex": 39
  },
  {
    "ref": "JRgx",
    "baseRef": "wnjI",
    "serverIndex": 40
  },
  {
    "ref": "_upA",
    "baseRef": "P6Q3",
    "serverIndex": 41
  },
  {
    "ref": "6WLJ",
    "baseRef": "jSwy",
    "serverIndex": 42
  },
  {
    "ref": "VCRW",
    "baseRef": "JRgx",
    "serverIndex": 43
  },
  {
    "ref": "wLET",
    "baseRef": "_upA",
    "serverIndex": 44
  },
  {
    "ref": "nXH0",
    "baseRef": "wLET",
    "serverIndex": 45
  },
  {
    "ref": "cjjU",
    "baseRef": "nXH0",
    "serverIndex": 46
  },
  {
    "ref": "xHVP",
    "baseRef": "cjjU",
    "serverIndex": 47
  },
  {
    "ref": "vNcP",
    "baseRef": "VCRW",
    "serverIndex": 48
  },
  {
    "ref": "Bdnx",
    "baseRef": "vNcP",
    "serverIndex": 49
  },
  {
    "ref": "Jme-",
    "baseRef": "Bdnx",
    "serverIndex": 50
  },
  {
    "ref": "FdEY",
    "baseRef": "Jme-",
    "serverIndex": 51
  },
  {
    "ref": "LDPX",
    "baseRef": "xHVP",
    "serverIndex": 52
  },
  {
    "ref": "ox6_",
    "baseRef": "FdEY",
    "serverIndex": 53
  },
  {
    "ref": "QviU",
    "baseRef": "LDPX",
    "serverIndex": 54
  },
  {
    "ref": "Ki4U",
    "baseRef": "6WLJ",
    "serverIndex": 55
  },
  {
    "ref": "1BEO",
    "baseRef": "QviU",
    "serverIndex": 56
  },
  {
    "ref": "a18B",
    "baseRef": "Ki4U",
    "serverIndex": 57
  },
  {
    "ref": "ybDt",
    "baseRef": "ox6_",
    "serverIndex": 58
  },
  {
    "ref": "GxOP",
    "baseRef": "a18B",
    "serverIndex": 59
  },
  {
    "ref": "aqly",
    "baseRef": "GxOP",
    "serverIndex": 60
  },
  {
    "ref": "L6n0",
    "baseRef": "1BEO",
    "serverIndex": 61
  },
  {
    "ref": "JtIO",
    "baseRef": "ybDt",
    "serverIndex": 62
  },
  {
    "ref": "qRyf",
    "baseRef": "JtIO",
    "serverIndex": 63
  },
  {
    "ref": "1_Tw",
    "baseRef": "L6n0",
    "serverIndex": 64
  },
  {
    "ref": "YOCf",
    "baseRef": "aqly",
    "serverIndex": 65
  },
  {
    "ref": "2vAw",
    "baseRef": "qRyf",
    "serverIndex": 66
  },
  {
    "ref": "Pn88",
    "baseRef": "1_Tw",
    "serverIndex": 67
  },
  {
    "ref": "JRbY",
    "baseRef": "YOCf",
    "serverIndex": 68
  },
  {
    "ref": "fQVP",
    "baseRef": "2vAw",
    "serverIndex": 69
  },
  {
    "ref": "GZwk",
    "baseRef": "Pn88",
    "serverIndex": 70
  },
  {
    "ref": "WEbg",
    "baseRef": "JRbY",
    "serverIndex": 71
  },
  {
    "ref": "4VL_",
    "baseRef": "fQVP",
    "serverIndex": 72
  },
  {
    "ref": "mS77",
    "baseRef": "GZwk",
    "serverIndex": 73
  },
  {
    "ref": "4CoO",
    "baseRef": "4VL_",
    "serverIndex": 74
  },
  {
    "ref": "mOuu",
    "baseRef": "mS77",
    "serverIndex": 75
  },
  {
    "ref": "XRFr",
    "baseRef": "4CoO",
    "serverIndex": 76
  },
  {
    "ref": "avxW",
    "baseRef": "WEbg",
    "serverIndex": 77
  },
  {
    "ref": "z7k7",
    "baseRef": "XRFr",
    "serverIndex": 78
  },
  {
    "ref": "KApi",
    "baseRef": "avxW",
    "serverIndex": 79
  },
  {
    "ref": "XoBp",
    "baseRef": "z7k7",
    "serverIndex": 80
  },
  {
    "ref": "-L4u",
    "baseRef": "KApi",
    "serverIndex": 81
  },
  {
    "ref": "1m7R",
    "baseRef": "mOuu",
    "serverIndex": 82
  },
  {
    "ref": "e6Tm",
    "baseRef": "XoBp",
    "serverIndex": 83
  },
  {
    "ref": "--Lx",
    "baseRef": "1m7R",
    "serverIndex": 84
  },
  {
    "ref": "prE2",
    "baseRef": "-L4u",
    "serverIndex": 85
  },
  {
    "ref": "nNJA",
    "baseRef": "prE2",
    "serverIndex": 86
  },
  {
    "ref": "XphG",
    "baseRef": "nNJA",
    "serverIndex": 87
  },
  {
    "ref": "c44N",
    "baseRef": "--Lx",
    "serverIndex": 88
  },
  {
    "ref": "sXf5",
    "baseRef": "c44N",
    "serverIndex": 89
  },
  {
    "ref": "JyeA",
    "baseRef": "sXf5",
    "serverIndex": 90
  },
  {
    "ref": "vM2M",
    "baseRef": "JyeA",
    "serverIndex": 91
  },
  {
    "ref": "2XwL",
    "baseRef": "XphG",
    "serverIndex": 92
  },
  {
    "ref": "1FU6",
    "baseRef": "e6Tm",
    "serverIndex": 93
  },
  {
    "ref": "7_hW",
    "baseRef": "vM2M",
    "serverIndex": 94
  },
  {
    "ref": "feTG",
    "baseRef": "1FU6",
    "serverIndex": 95
  },
  {
    "ref": "nz16",
    "baseRef": "2XwL",
    "serverIndex": 96
  },
  {
    "ref": "Npd9",
    "baseRef": "7_hW",
    "serverIndex": 97
  },
  {
    "ref": "u7oq",
    "baseRef": "nz16",
    "serverIndex": 98
  },
  {
    "ref": "ENdQ",
    "baseRef": "u7oq",
    "serverIndex": 99
  },
  {
    "ref": "ijWy",
    "baseRef": "feTG",
    "serverIndex": 100
  },
  {
    "ref": "KQ1A",
    "baseRef": "ENdQ",
    "serverIndex": 101
  },
  {
    "ref": "HvWb",
    "baseRef": "KQ1A",
    "serverIndex": 102
  },
  {
    "ref": "xBhx",
    "baseRef": "Npd9",
    "serverIndex": 103
  },
  {
    "ref": "cuOI",
    "baseRef": "ijWy",
    "serverIndex": 104
  },
  {
    "ref": "9r3V",
    "baseRef": "cuOI",
    "serverIndex": 105
  },
  {
    "ref": "yjQl",
    "baseRef": "9r3V",
    "serverIndex": 106
  },
  {
    "ref": "7Caw",
    "baseRef": "HvWb",
    "serverIndex": 107
  },
  {
    "ref": "BzvK",
    "baseRef": "xBhx",
    "serverIndex": 108
  },
  {
    "ref": "ssvR",
    "baseRef": "yjQl",
    "serverIndex": 109
  },
  {
    "ref": "rrsu",
    "baseRef": "7Caw",
    "serverIndex": 110
  },
  {
    "ref": "At3F",
    "baseRef": "BzvK",
    "serverIndex": 111
  },
  {
    "ref": "rS44",
    "baseRef": "ssvR",
    "serverIndex": 112
  },
  {
    "ref": "OTPq",
    "baseRef": "rrsu",
    "serverIndex": 113
  },
  {
    "ref": "ELPz",
    "baseRef": "OTPq",
    "serverIndex": 114
  },
  {
    "ref": "nEqm",
    "baseRef": "ELPz",
    "serverIndex": 115
  },
  {
    "ref": "sTFU",
    "baseRef": "nEqm",
    "serverIndex": 116
  },
  {
    "ref": "EXFP",
    "baseRef": "sTFU",
    "serverIndex": 117
  },
  {
    "ref": "3T3Y",
    "baseRef": "At3F",
    "serverIndex": 118
  },
  {
    "ref": "SMEn",
    "baseRef": "rS44",
    "serverIndex": 119
  },
  {
    "ref": "2BF4",
    "baseRef": "EXFP",
    "serverIndex": 120
  },
  {
    "ref": "TK_J",
    "baseRef": "SMEn",
    "serverIndex": 121
  },
  {
    "ref": "euJY",
    "baseRef": "3T3Y",
    "serverIndex": 122
  },
  {
    "ref": "xsfu",
    "baseRef": "2BF4",
    "serverIndex": 123
  },
  {
    "ref": "EWhL",
    "baseRef": "TK_J",
    "serverIndex": 124
  },
  {
    "ref": "UfXn",
    "baseRef": "euJY",
    "serverIndex": 125
  },
  {
    "ref": "wBqu",
    "baseRef": "xsfu",
    "serverIndex": 126
  },
  {
    "ref": "0O35",
    "baseRef": "EWhL",
    "serverIndex": 127
  },
  {
    "ref": "S2v9",
    "baseRef": "wBqu",
    "serverIndex": 128
  },
  {
    "ref": "0G_Z",
    "baseRef": "UfXn",
    "serverIndex": 129
  },
  {
    "ref": "ysAJ",
    "baseRef": "0O35",
    "serverIndex": 130
  },
  {
    "ref": "nXaH",
    "baseRef": "S2v9",
    "serverIndex": 131
  },
  {
    "ref": "lnp0",
    "baseRef": "0G_Z",
    "serverIndex": 132
  },
  {
    "ref": "Ry_s",
    "baseRef": "lnp0",
    "serverIndex": 133
  },
  {
    "ref": "lBlF",
    "baseRef": "ysAJ",
    "serverIndex": 134
  },
  {
    "ref": "03uO",
    "baseRef": "nXaH",
    "serverIndex": 135
  },
  {
    "ref": "MHKk",
    "baseRef": "Ry_s",
    "serverIndex": 136
  },
  {
    "ref": "xVaN",
    "baseRef": "lBlF",
    "serverIndex": 137
  },
  {
    "ref": "NB20",
    "baseRef": "MHKk",
    "serverIndex": 138
  },
  {
    "ref": "vuFz",
    "baseRef": "xVaN",
    "serverIndex": 139
  },
  {
    "ref": "lEFC",
    "baseRef": "NB20",
    "serverIndex": 140
  },
  {
    "ref": "C62c",
    "baseRef": "vuFz",
    "serverIndex": 141
  },
  {
    "ref": "OXSs",
    "baseRef": "lEFC",
    "serverIndex": 142
  },
  {
    "ref": "2HRk",
    "baseRef": "C62c",
    "serverIndex": 143
  },
  {
    "ref": "F7WA",
    "baseRef": "2HRk",
    "serverIndex": 144
  },
  {
    "ref": "VPB8",
    "baseRef": "OXSs",
    "serverIndex": 145
  },
  {
    "ref": "ziNr",
    "baseRef": "03uO",
    "serverIndex": 146
  },
  {
    "ref": "Q3xQ",
    "baseRef": "F7WA",
    "serverIndex": 147
  },
  {
    "ref": "zG8b",
    "baseRef": "VPB8",
    "serverIndex": 148
  },
  {
    "ref": "LG1Q",
    "baseRef": "Q3xQ",
    "serverIndex": 149
  },
  {
    "ref": "nN4u",
    "baseRef": "LG1Q",
    "serverIndex": 150
  },
  {
    "ref": "T-mu",
    "baseRef": "ziNr",
    "serverIndex": 151
  },
  {
    "ref": "cg22",
    "baseRef": "nN4u",
    "serverIndex": 152
  },
  {
    "ref": "qGXk",
    "baseRef": "T-mu",
    "serverIndex": 153
  },
  {
    "ref": "0G8G",
    "baseRef": "cg22",
    "serverIndex": 154
  },
  {
    "ref": "Ezw-",
    "baseRef": "zG8b",
    "serverIndex": 155
  },
  {
    "ref": "_qBq",
    "baseRef": "qGXk",
    "serverIndex": 156
  },
  {
    "ref": "xfMv",
    "baseRef": "0G8G",
    "serverIndex": 157
  },
  {
    "ref": "5nHL",
    "baseRef": "Ezw-",
    "serverIndex": 158
  },
  {
    "ref": "i_Fh",
    "baseRef": "xfMv",
    "serverIndex": 159
  },
  {
    "ref": "BctB",
    "baseRef": "i_Fh",
    "serverIndex": 160
  },
  {
    "ref": "-Paf",
    "baseRef": "BctB",
    "serverIndex": 161
  },
  {
    "ref": "szF1",
    "baseRef": "5nHL",
    "serverIndex": 162
  },
  {
    "ref": "ZdZc",
    "baseRef": "szF1",
    "serverIndex": 163
  },
  {
    "ref": "44cP",
    "baseRef": "_qBq",
    "serverIndex": 164
  },
  {
    "ref": "sH19",
    "baseRef": "-Paf",
    "serverIndex": 165
  },
  {
    "ref": "_mD3",
    "baseRef": "ZdZc",
    "serverIndex": 166
  },
  {
    "ref": "nEW7",
    "baseRef": "44cP",
    "serverIndex": 167
  },
  {
    "ref": "3qp5",
    "baseRef": "sH19",
    "serverIndex": 168
  },
  {
    "ref": "XDty",
    "baseRef": "_mD3",
    "serverIndex": 169
  },
  {
    "ref": "Ppg-",
    "baseRef": "nEW7",
    "serverIndex": 170
  },
  {
    "ref": "eCcB",
    "baseRef": "3qp5",
    "serverIndex": 171
  },
  {
    "ref": "kv7u",
    "baseRef": "XDty",
    "serverIndex": 172
  },
  {
    "ref": "0Q_u",
    "baseRef": "eCcB",
    "serverIndex": 173
  },
  {
    "ref": "MAjW",
    "baseRef": "kv7u",
    "serverIndex": 174
  },
  {
    "ref": "WrfS",
    "baseRef": "0Q_u",
    "serverIndex": 175
  },
  {
    "ref": "yWzx",
    "baseRef": "MAjW",
    "serverIndex": 176
  },
  {
    "ref": "w-5T",
    "baseRef": "WrfS",
    "serverIndex": 177
  },
  {
    "ref": "o4Io",
    "baseRef": "Ppg-",
    "serverIndex": 178
  },
  {
    "ref": "FAlt",
    "baseRef": "yWzx",
    "serverIndex": 179
  },
  {
    "ref": "2dgL",
    "baseRef": "w-5T",
    "serverIndex": 180
  },
  {
    "ref": "xYbj",
    "baseRef": "o4Io",
    "serverIndex": 181
  },
  {
    "ref": "UK6c",
    "baseRef": "FAlt",
    "serverIndex": 182
  },
  {
    "ref": "fnmW",
    "baseRef": "2dgL",
    "serverIndex": 183
  },
  {
    "ref": "Uut-",
    "baseRef": "xYbj",
    "serverIndex": 184
  },
  {
    "ref": "rhtw",
    "baseRef": "UK6c",
    "serverIndex": 185
  },
  {
    "ref": "C5ch",
    "baseRef": "rhtw",
    "serverIndex": 186
  },
  {
    "ref": "K8__",
    "baseRef": "C5ch",
    "serverIndex": 187
  },
  {
    "ref": "-ScR",
    "baseRef": "K8__",
    "serverIndex": 188
  },
  {
    "ref": "m65f",
    "baseRef": "-ScR",
    "serverIndex": 189
  },
  {
    "ref": "j71A",
    "baseRef": "m65f",
    "serverIndex": 190
  },
  {
    "ref": "NAm0",
    "baseRef": "Uut-",
    "serverIndex": 191
  },
  {
    "ref": "YSPf",
    "baseRef": "NAm0",
    "serverIndex": 192
  },
  {
    "ref": "0hCG",
    "baseRef": "fnmW",
    "serverIndex": 193
  },
  {
    "ref": "R2tl",
    "baseRef": "j71A",
    "serverIndex": 194
  },
  {
    "ref": "7SCP",
    "baseRef": "0hCG",
    "serverIndex": 195
  },
  {
    "ref": "PKtD",
    "baseRef": "R2tl",
    "serverIndex": 196
  },
  {
    "ref": "k3-g",
    "baseRef": "7SCP",
    "serverIndex": 197
  },
  {
    "ref": "TcEU",
    "baseRef": "PKtD",
    "serverIndex": 198
  },
  {
    "ref": "R8az",
    "baseRef": "k3-g",
    "serverIndex": 199
  },
  {
    "ref": "J_Ao",
    "baseRef": "YSPf",
    "serverIndex": 200
  },
  {
    "ref": "9WDz",
    "baseRef": "TcEU",
    "serverIndex": 201
  },
  {
    "ref": "gdo2",
    "baseRef": "R8az",
    "serverIndex": 202
  },
  {
    "ref": "BaVw",
    "baseRef": "J_Ao",
    "serverIndex": 203
  },
  {
    "ref": "p4Xt",
    "baseRef": "9WDz",
    "serverIndex": 204
  },
  {
    "ref": "9Y0E",
    "baseRef": "gdo2",
    "serverIndex": 205
  },
  {
    "ref": "s-y_",
    "baseRef": "BaVw",
    "serverIndex": 206
  },
  {
    "ref": "3Fpm",
    "baseRef": "p4Xt",
    "serverIndex": 207
  },
  {
    "ref": "ztlc",
    "baseRef": "9Y0E",
    "serverIndex": 208
  },
  {
    "ref": "sZ8X",
    "baseRef": "3Fpm",
    "serverIndex": 209
  },
  {
    "ref": "nNU_",
    "baseRef": "ztlc",
    "serverIndex": 210
  },
  {
    "ref": "poCv",
    "baseRef": "sZ8X",
    "serverIndex": 211
  },
  {
    "ref": "OcA-",
    "baseRef": "nNU_",
    "serverIndex": 212
  },
  {
    "ref": "sNAz",
    "baseRef": "s-y_",
    "serverIndex": 213
  },
  {
    "ref": "rZ51",
    "baseRef": "OcA-",
    "serverIndex": 214
  },
  {
    "ref": "rkOT",
    "baseRef": "poCv",
    "serverIndex": 215
  },
  {
    "ref": "L3dq",
    "baseRef": "rZ51",
    "serverIndex": 216
  },
  {
    "ref": "3LFi",
    "baseRef": "sNAz",
    "serverIndex": 217
  },
  {
    "ref": "SBcJ",
    "baseRef": "L3dq",
    "serverIndex": 218
  },
  {
    "ref": "Ql-H",
    "baseRef": "rkOT",
    "serverIndex": 219
  },
  {
    "ref": "axqU",
    "baseRef": "3LFi",
    "serverIndex": 220
  },
  {
    "ref": "nxQO",
    "baseRef": "SBcJ",
    "serverIndex": 221
  },
  {
    "ref": "g8v8",
    "baseRef": "axqU",
    "serverIndex": 222
  },
  {
    "ref": "_LIl",
    "baseRef": "g8v8",
    "serverIndex": 223
  },
  {
    "ref": "XgM-",
    "baseRef": "_LIl",
    "serverIndex": 224
  },
  {
    "ref": "z6rB",
    "baseRef": "XgM-",
    "serverIndex": 225
  },
  {
    "ref": "b0Kj",
    "baseRef": "z6rB",
    "serverIndex": 226
  },
  {
    "ref": "xXDZ",
    "baseRef": "nxQO",
    "serverIndex": 227
  },
  {
    "ref": "oc0l",
    "baseRef": "b0Kj",
    "serverIndex": 228
  },
  {
    "ref": "3kWk",
    "baseRef": "Ql-H",
    "serverIndex": 229
  },
  {
    "ref": "0hXJ",
    "baseRef": "xXDZ",
    "serverIndex": 230
  },
  {
    "ref": "SQWs",
    "baseRef": "oc0l",
    "serverIndex": 231
  },
  {
    "ref": "J9qZ",
    "baseRef": "SQWs",
    "serverIndex": 232
  },
  {
    "ref": "WshV",
    "baseRef": "J9qZ",
    "serverIndex": 233
  },
  {
    "ref": "83Vh",
    "baseRef": "WshV",
    "serverIndex": 234
  },
  {
    "ref": "uchE",
    "baseRef": "83Vh",
    "serverIndex": 235
  },
  {
    "ref": "PxXx",
    "baseRef": "3kWk",
    "serverIndex": 236
  },
  {
    "ref": "S0vF",
    "baseRef": "uchE",
    "serverIndex": 237
  },
  {
    "ref": "MwKI",
    "baseRef": "0hXJ",
    "serverIndex": 238
  },
  {
    "ref": "NWIu",
    "baseRef": "PxXx",
    "serverIndex": 239
  },
  {
    "ref": "q6r5",
    "baseRef": "S0vF",
    "serverIndex": 240
  },
  {
    "ref": "qCl4",
    "baseRef": "MwKI",
    "serverIndex": 241
  },
  {
    "ref": "Lrri",
    "baseRef": "q6r5",
    "serverIndex": 242
  },
  {
    "ref": "-ATS",
    "baseRef": "qCl4",
    "serverIndex": 243
  },
  {
    "ref": "F28N",
    "baseRef": "NWIu",
    "serverIndex": 244
  },
  {
    "ref": "oSeg",
    "baseRef": "Lrri",
    "serverIndex": 245
  },
  {
    "ref": "aA2R",
    "baseRef": "-ATS",
    "serverIndex": 246
  },
  {
    "ref": "WEQ3",
    "baseRef": "oSeg",
    "serverIndex": 247
  },
  {
    "ref": "ufoQ",
    "baseRef": "WEQ3",
    "serverIndex": 248
  },
  {
    "ref": "_0tT",
    "baseRef": "aA2R",
    "serverIndex": 249
  },
  {
    "ref": "Fkfi",
    "baseRef": "_0tT",
    "serverIndex": 250
  },
  {
    "ref": "T02X",
    "baseRef": "Fkfi",
    "serverIndex": 251
  },
  {
    "ref": "bAHB",
    "baseRef": "T02X",
    "serverIndex": 252
  },
  {
    "ref": "1aO_",
    "baseRef": "bAHB",
    "serverIndex": 253
  },
  {
    "ref": "7a9I",
    "baseRef": "F28N",
    "serverIndex": 254
  },
  {
    "ref": "5IL1",
    "baseRef": "7a9I",
    "serverIndex": 255
  },
  {
    "ref": "db81",
    "baseRef": "1aO_",
    "serverIndex": 256
  },
  {
    "ref": "l7as",
    "baseRef": "db81",
    "serverIndex": 257
  },
  {
    "ref": "O2hS",
    "baseRef": "l7as",
    "serverIndex": 258
  },
  {
    "ref": "aYKE",
    "baseRef": "5IL1",
    "serverIndex": 259
  },
  {
    "ref": "Fhn3",
    "baseRef": "O2hS",
    "serverIndex": 260
  },
  {
    "ref": "4ANK",
    "baseRef": "aYKE",
    "serverIndex": 261
  },
  {
    "ref": "S36H",
    "baseRef": "ufoQ",
    "serverIndex": 262
  },
  {
    "ref": "sJhh",
    "baseRef": "Fhn3",
    "serverIndex": 263
  },
  {
    "ref": "bGbD",
    "baseRef": "4ANK",
    "serverIndex": 264
  },
  {
    "ref": "bcrJ",
    "baseRef": "S36H",
    "serverIndex": 265
  },
  {
    "ref": "HP1u",
    "baseRef": "sJhh",
    "serverIndex": 266
  },
  {
    "ref": "VuFY",
    "baseRef": "HP1u",
    "serverIndex": 267
  },
  {
    "ref": "grsm",
    "baseRef": "VuFY",
    "serverIndex": 268
  },
  {
    "ref": "COjd",
    "baseRef": "bGbD",
    "serverIndex": 269
  },
  {
    "ref": "q4Qw",
    "baseRef": "bcrJ",
    "serverIndex": 270
  },
  {
    "ref": "E9Ej",
    "baseRef": "grsm",
    "serverIndex": 271
  },
  {
    "ref": "ROVM",
    "baseRef": "COjd",
    "serverIndex": 272
  },
  {
    "ref": "QEw_",
    "baseRef": "q4Qw",
    "serverIndex": 273
  },
  {
    "ref": "_D0d",
    "baseRef": "E9Ej",
    "serverIndex": 274
  },
  {
    "ref": "v7yl",
    "baseRef": "ROVM",
    "serverIndex": 275
  },
  {
    "ref": "CvRA",
    "baseRef": "v7yl",
    "serverIndex": 276
  },
  {
    "ref": "3PMV",
    "baseRef": "QEw_",
    "serverIndex": 277
  },
  {
    "ref": "61a4",
    "baseRef": "_D0d",
    "serverIndex": 278
  },
  {
    "ref": "Jekk",
    "baseRef": "CvRA",
    "serverIndex": 279
  },
  {
    "ref": "OXza",
    "baseRef": "3PMV",
    "serverIndex": 280
  },
  {
    "ref": "X3J6",
    "baseRef": "61a4",
    "serverIndex": 281
  },
  {
    "ref": "uCeg",
    "baseRef": "Jekk",
    "serverIndex": 282
  },
  {
    "ref": "wVUG",
    "baseRef": "uCeg",
    "serverIndex": 283
  },
  {
    "ref": "V0p2",
    "baseRef": "OXza",
    "serverIndex": 284
  },
  {
    "ref": "U5Md",
    "baseRef": "X3J6",
    "serverIndex": 285
  },
  {
    "ref": "qafW",
    "baseRef": "wVUG",
    "serverIndex": 286
  },
  {
    "ref": "yscm",
    "baseRef": "V0p2",
    "serverIndex": 287
  },
  {
    "ref": "zqhI",
    "baseRef": "U5Md",
    "serverIndex": 288
  },
  {
    "ref": "UBpK",
    "baseRef": "qafW",
    "serverIndex": 289
  },
  {
    "ref": "Y2vQ",
    "baseRef": "yscm",
    "serverIndex": 290
  },
  {
    "ref": "NM4H",
    "baseRef": "zqhI",
    "serverIndex": 291
  },
  {
    "ref": "i2Mm",
    "baseRef": "Y2vQ",
    "serverIndex": 292
  },
  {
    "ref": "t32S",
    "baseRef": "NM4H",
    "serverIndex": 293
  },
  {
    "ref": "2hTL",
    "baseRef": "UBpK",
    "serverIndex": 294
  },
  {
    "ref": "kmIu",
    "baseRef": "i2Mm",
    "serverIndex": 295
  },
  {
    "ref": "h3Fm",
    "baseRef": "t32S",
    "serverIndex": 296
  },
  {
    "ref": "TaQj",
    "baseRef": "h3Fm",
    "serverIndex": 297
  },
  {
    "ref": "2XZY",
    "baseRef": "TaQj",
    "serverIndex": 298
  },
  {
    "ref": "TsFL",
    "baseRef": "kmIu",
    "serverIndex": 299
  },
  {
    "ref": "NJYm",
    "baseRef": "2hTL",
    "serverIndex": 300
  },
  {
    "ref": "-vNH",
    "baseRef": "2XZY",
    "serverIndex": 301
  },
  {
    "ref": "dYFM",
    "baseRef": "TsFL",
    "serverIndex": 302
  },
  {
    "ref": "Eg54",
    "baseRef": "NJYm",
    "serverIndex": 303
  },
  {
    "ref": "LaRH",
    "baseRef": "-vNH",
    "serverIndex": 304
  },
  {
    "ref": "4kh5",
    "baseRef": "Eg54",
    "serverIndex": 305
  },
  {
    "ref": "2H5n",
    "baseRef": "4kh5",
    "serverIndex": 306
  },
  {
    "ref": "UEuS",
    "baseRef": "LaRH",
    "serverIndex": 307
  },
  {
    "ref": "UBrQ",
    "baseRef": "dYFM",
    "serverIndex": 308
  },
  {
    "ref": "5oVp",
    "baseRef": "UEuS",
    "serverIndex": 309
  },
  {
    "ref": "Gjxh",
    "baseRef": "UBrQ",
    "serverIndex": 310
  },
  {
    "ref": "0_AM",
    "baseRef": "Gjxh",
    "serverIndex": 311
  },
  {
    "ref": "ucrt",
    "baseRef": "5oVp",
    "serverIndex": 312
  },
  {
    "ref": "qFlP",
    "baseRef": "ucrt",
    "serverIndex": 313
  },
  {
    "ref": "xoo9",
    "baseRef": "0_AM",
    "serverIndex": 314
  },
  {
    "ref": "QQk3",
    "baseRef": "2H5n",
    "serverIndex": 315
  },
  {
    "ref": "Pglx",
    "baseRef": "qFlP",
    "serverIndex": 316
  },
  {
    "ref": "2aoj",
    "baseRef": "Pglx",
    "serverIndex": 317
  },
  {
    "ref": "Zqeh",
    "baseRef": "QQk3",
    "serverIndex": 318
  },
  {
    "ref": "0dzV",
    "baseRef": "xoo9",
    "serverIndex": 319
  },
  {
    "ref": "SFhp",
    "baseRef": "0dzV",
    "serverIndex": 320
  },
  {
    "ref": "Sj4m",
    "baseRef": "Zqeh",
    "serverIndex": 321
  },
  {
    "ref": "wAEs",
    "baseRef": "Sj4m",
    "serverIndex": 322
  },
  {
    "ref": "xV3p",
    "baseRef": "2aoj",
    "serverIndex": 323
  },
  {
    "ref": "O7oT",
    "baseRef": "SFhp",
    "serverIndex": 324
  },
  {
    "ref": "OJmq",
    "baseRef": "wAEs",
    "serverIndex": 325
  },
  {
    "ref": "ykC1",
    "baseRef": "xV3p",
    "serverIndex": 326
  },
  {
    "ref": "hWj1",
    "baseRef": "O7oT",
    "serverIndex": 327
  },
  {
    "ref": "u6xK",
    "baseRef": "OJmq",
    "serverIndex": 328
  },
  {
    "ref": "iFxL",
    "baseRef": "ykC1",
    "serverIndex": 329
  },
  {
    "ref": "q5Fk",
    "baseRef": "hWj1",
    "serverIndex": 330
  },
  {
    "ref": "XKFi",
    "baseRef": "iFxL",
    "serverIndex": 331
  },
  {
    "ref": "tROF",
    "baseRef": "q5Fk",
    "serverIndex": 332
  },
  {
    "ref": "gA7u",
    "baseRef": "XKFi",
    "serverIndex": 333
  },
  {
    "ref": "ke-Z",
    "baseRef": "u6xK",
    "serverIndex": 334
  },
  {
    "ref": "f3T8",
    "baseRef": "tROF",
    "serverIndex": 335
  },
  {
    "ref": "vZXo",
    "baseRef": "ke-Z",
    "serverIndex": 336
  },
  {
    "ref": "i2IB",
    "baseRef": "f3T8",
    "serverIndex": 337
  },
  {
    "ref": "Ksze",
    "baseRef": "vZXo",
    "serverIndex": 338
  },
  {
    "ref": "pvEP",
    "baseRef": "i2IB",
    "serverIndex": 339
  },
  {
    "ref": "5F15",
    "baseRef": "Ksze",
    "serverIndex": 340
  },
  {
    "ref": "LP5s",
    "baseRef": "pvEP",
    "serverIndex": 341
  },
  {
    "ref": "eNa7",
    "baseRef": "LP5s",
    "serverIndex": 342
  },
  {
    "ref": "Nohw",
    "baseRef": "5F15",
    "serverIndex": 343
  },
  {
    "ref": "xUBG",
    "baseRef": "gA7u",
    "serverIndex": 344
  },
  {
    "ref": "AG07",
    "baseRef": "eNa7",
    "serverIndex": 345
  },
  {
    "ref": "jUgI",
    "baseRef": "Nohw",
    "serverIndex": 346
  },
  {
    "ref": "mLl3",
    "baseRef": "AG07",
    "serverIndex": 347
  },
  {
    "ref": "R5rK",
    "baseRef": "jUgI",
    "serverIndex": 348
  },
  {
    "ref": "QIr-",
    "baseRef": "mLl3",
    "serverIndex": 349
  },
  {
    "ref": "FTDu",
    "baseRef": "R5rK",
    "serverIndex": 350
  },
  {
    "ref": "bbpQ",
    "baseRef": "FTDu",
    "serverIndex": 351
  },
  {
    "ref": "Vvml",
    "baseRef": "xUBG",
    "serverIndex": 352
  },
  {
    "ref": "65jv",
    "baseRef": "QIr-",
    "serverIndex": 353
  },
  {
    "ref": "lonN",
    "baseRef": "Vvml",
    "serverIndex": 354
  },
  {
    "ref": "P_x9",
    "baseRef": "65jv",
    "serverIndex": 355
  },
  {
    "ref": "FMG7",
    "baseRef": "P_x9",
    "serverIndex": 356
  },
  {
    "ref": "EYka",
    "baseRef": "bbpQ",
    "serverIndex": 357
  },
  {
    "ref": "SDPR",
    "baseRef": "lonN",
    "serverIndex": 358
  },
  {
    "ref": "FMnd",
    "baseRef": "FMG7",
    "serverIndex": 359
  },
  {
    "ref": "K1u5",
    "baseRef": "FMnd",
    "serverIndex": 360
  },
  {
    "ref": "0oFm",
    "baseRef": "xBhx",
    "mergeRef": "9r3V",
    "serverIndex": 361
  },
  {
    "ref": "OVzD",
    "baseRef": "0oFm",
    "mergeRef": "K1u5",
    "serverIndex": 362
  },
  {
    "ref": "Ug7i",
    "baseRef": "OVzD",
    "serverIndex": 363
  },
  {
    "ref": "lP5F",
    "baseRef": "HvWb",
    "mergeRef": "xBhx",
    "serverIndex": 364
  },
  {
    "ref": "eVOn",
    "baseRef": "SDPR",
    "mergeRef": "lP5F",
    "serverIndex": 365
  },
  {
    "ref": "MBQU",
    "baseRef": "eVOn",
    "serverIndex": 366
  },
  {
    "ref": "Hcf8",
    "baseRef": "MBQU",
    "serverIndex": 367
  },
  {
    "ref": "Xvk4",
    "baseRef": "Hcf8",
    "serverIndex": 368
  }
]
